[{"team": "Bayern Munchen", "points": 18}, {"team": "Borussia Dortmund", "points": 18}, {"team": "TSG 1899 Hoffenheim", "points": 18}, {"team": "RB Leipzig", "points": 18}, {"team": "Eintracht Frankfurt", "points": 18}, {"team": "Borussia M'gladbach", "points": 18}, {"team": "Bayer 04 Leverkusen", "points": 18}, {"team": "Werder Bremen", "points": 3}, {"team": "FC Augsburg", "points": 18}, {"team": "VfL Wolfsburg", "points": 3}, {"team": "FC Union Berlin", "points": 3}, {"team": "FC Schalke 04", "points": 3}, {"team": "FC Koln", "points": 3}, {"team": "SC Freiburg", "points": 3}, {"team": "Hertha BSC", "points": 3}, {"team": "FSV Mainz 05", "points": 18}, {"team": "Arminia Bielefeld", "points": 3}, {"team": "VFB Stuttgart", "points": 3}]